[
  {
    "Name": "Wohnzimmer",
    "Lights": [
      {
        "Name": "RGB",
        "Channels": [
          {
            "Name": "33",
            "Type": "Range",
            "Target": "ArtNet",
            "Min": 0.0,
            "Max": 255.0,
            "Value": 0.0,
            "CanBeModified": true
          },
          {
            "Name": "34",
            "Type": "Range",
            "Target": "ArtNet",
            "Min": 0.0,
            "Max": 255.0,
            "Value": 0.0,
            "CanBeModified": true
          },
          {
            "Name": "35",
            "Type": "Range",
            "Target": "ArtNet",
            "Min": 0.0,
            "Max": 255.0,
            "Value": 0.0,
            "CanBeModified": true
          }
        ]
      },
      {
        "Name": "Weiß",
        "Channels": [
          {
            "Name": "36",
            "Type": "Range",
            "Target": "ArtNet",
            "Min": 0.0,
            "Max": 255.0,
            "Value": 51.0,
            "CanBeModified": true
          }
        ]
      },
      {
        "Name": "Küche",
        "Channels": [
          {
            "Name": "37",
            "Type": "Range",
            "Target": "ArtNet",
            "Min": 0.0,
            "Max": 255.0,
            "Value": 0.0,
            "CanBeModified": true
          }
        ]
      }
    ],
    "Temperatures": [
      {
        "Name": "Temperatur",
        "MeasuredTemperature": {
          "Name": "MeasuredTemperatureWohnzimmer",
          "Type": "Range",
          "Target": "Temperature",
          "Min": 0.0,
          "Max": 0.0,
          "Value": 0.0,
          "CanBeModified": false
        },
        "TargetTemperature": {
          "Name": "TargetTemperatureWohnzimmer",
          "Type": "Range",
          "Target": "Temperature",
          "Min": 0.0,
          "Max": 30.0,
          "Value": 0.0,
          "CanBeModified": true
        }
      }
    ]
  },
  {
    "Name": "Bad",
    "Lights": [
      {
        "Name": "Weiß",
        "Channels": [
          {
            "Name": "16",
            "Type": "Range",
            "Target": "ArtNet",
            "Min": 0.0,
            "Max": 255.0,
            "Value": 0.0,
            "CanBeModified": true
          }
        ]
      }
    ],
    "Temperatures": [
      {
        "Name": "Temperatur",
        "MeasuredTemperature": {
          "Name": "MeasuredTemperatureBad",
          "Type": "Range",
          "Target": "Temperature",
          "Min": 0.0,
          "Max": 0.0,
          "Value": 0.0,
          "CanBeModified": false
        },
        "TargetTemperature": {
          "Name": "TargetTemperatureBad",
          "Type": "Range",
          "Target": "Temperature",
          "Min": 0.0,
          "Max": 30.0,
          "Value": 0.0,
          "CanBeModified": true
        }
      }
    ]
  },
  {
    "Name": "WC",
    "Lights": [
      {
        "Name": "Weiß",
        "Channels": [
          {
            "Name": "28",
            "Type": "Range",
            "Target": "ArtNet",
            "Min": 0.0,
            "Max": 255.0,
            "Value": 0.0,
            "CanBeModified": true
          }
        ]
      }
    ],
    "Temperatures": [
      {
        "Name": "Temperatur",
        "MeasuredTemperature": {
          "Name": "MeasuredTemperatureWC",
          "Type": "Range",
          "Target": "Temperature",
          "Min": 0.0,
          "Max": 0.0,
          "Value": 0.0,
          "CanBeModified": false
        },
        "TargetTemperature": {
          "Name": "TargetTemperatureWC",
          "Type": "Range",
          "Target": "Temperature",
          "Min": 0.0,
          "Max": 30.0,
          "Value": 0.0,
          "CanBeModified": true
        }
      }
    ]
  },
  {
    "Name": "Flur",
    "Lights": [
      {
        "Name": "Weiß",
        "Channels": [
          {
            "Name": "12",
            "Type": "Range",
            "Target": "ArtNet",
            "Min": 0.0,
            "Max": 255.0,
            "Value": 0.0,
            "CanBeModified": true
          }
        ]
      }
    ],
    "Temperatures": [
      {
        "Name": "Temperatur",
        "MeasuredTemperature": {
          "Name": "MeasuredTemperatureFlur",
          "Type": "Range",
          "Target": "Temperature",
          "Min": 0.0,
          "Max": 0.0,
          "Value": 0.0,
          "CanBeModified": false
        },
        "TargetTemperature": {
          "Name": "TargetTemperatureFlur",
          "Type": "Range",
          "Target": "Temperature",
          "Min": 0.0,
          "Max": 30.0,
          "Value": 0.0,
          "CanBeModified": true
        }
      }
    ]
  },
  {
    "Name": "Schlafzimmer",
    "Lights": [
      {
        "Name": "Weiß",
        "Channels": [
          {
            "Name": "32",
            "Type": "Range",
            "Target": "ArtNet",
            "Min": 0.0,
            "Max": 255.0,
            "Value": 0.0,
            "CanBeModified": true
          }
        ]
      }
    ],
    "Temperatures": [
      {
        "Name": "Temperatur",
        "MeasuredTemperature": {
          "Name": "MeasuredTemperatureSchlafzimmer",
          "Type": "Range",
          "Target": "Temperature",
          "Min": 0.0,
          "Max": 0.0,
          "Value": 0.0,
          "CanBeModified": false
        },
        "TargetTemperature": {
          "Name": "TargetTemperatureSchlafzimmer",
          "Type": "Range",
          "Target": "Temperature",
          "Min": 0.0,
          "Max": 30.0,
          "Value": 0.0,
          "CanBeModified": true
        }
      }
    ]
  },
  {
    "Name": "Ankleide",
    "Lights": [
      {
        "Name": "Weiß",
        "Channels": [
          {
            "Name": "24",
            "Type": "Range",
            "Target": "ArtNet",
            "Min": 0.0,
            "Max": 255.0,
            "Value": 0.0,
            "CanBeModified": true
          }
        ]
      }
    ],
    "Temperatures": [
      {
        "Name": "Temperatur",
        "MeasuredTemperature": {
          "Name": "MeasuredTemperatureAnkleide",
          "Type": "Range",
          "Target": "Temperature",
          "Min": 0.0,
          "Max": 0.0,
          "Value": 0.0,
          "CanBeModified": false
        },
        "TargetTemperature": {
          "Name": "TargetTemperatureAnkleide",
          "Type": "Range",
          "Target": "Temperature",
          "Min": 0.0,
          "Max": 30.0,
          "Value": 0.0,
          "CanBeModified": true
        }
      }
    ]
  },
  {
    "Name": "Gästezimmer",
    "Lights": [
      {
        "Name": "Weiß",
        "Channels": [
          {
            "Name": "20",
            "Type": "Range",
            "Target": "ArtNet",
            "Min": 0.0,
            "Max": 255.0,
            "Value": 0.0,
            "CanBeModified": true
          }
        ]
      }
    ],
    "Temperatures": [
      {
        "Name": "Temperatur",
        "MeasuredTemperature": {
          "Name": "MeasuredTemperatureGästezimmer",
          "Type": "Range",
          "Target": "Temperature",
          "Min": 0.0,
          "Max": 0.0,
          "Value": 0.0,
          "CanBeModified": false
        },
        "TargetTemperature": {
          "Name": "TargetTemperatureGästezimmer",
          "Type": "Range",
          "Target": "Temperature",
          "Min": 0.0,
          "Max": 30.0,
          "Value": 0.0,
          "CanBeModified": true
        }
      }
    ]
  },
  {
    "Name": "Kinderzimmer",
    "Lights": [
      {
        "Name": "Weiß",
        "Channels": [
          {
            "Name": "8",
            "Type": "Range",
            "Target": "ArtNet",
            "Min": 0.0,
            "Max": 255.0,
            "Value": 0.0,
            "CanBeModified": true
          }
        ]
      }
    ],
    "Temperatures": [
      {
        "Name": "Temperatur",
        "MeasuredTemperature": {
          "Name": "MeasuredTemperatureKinderzimmer",
          "Type": "Range",
          "Target": "Temperature",
          "Min": 0.0,
          "Max": 0.0,
          "Value": 0.0,
          "CanBeModified": false
        },
        "TargetTemperature": {
          "Name": "TargetTemperatureKinderzimmer",
          "Type": "Range",
          "Target": "Temperature",
          "Min": 0.0,
          "Max": 30.0,
          "Value": 0.0,
          "CanBeModified": true
        }
      }
    ]
  }
]